{"/_app":"pages/_app.js","/_error":"pages/_error.js","/Be":"pages/Be.html","/Detail":"pages/Detail.html","/Find":"pages/Find.html","/FindVolunteer":"pages/FindVolunteer.html","/First":"pages/First.html","/Join":"pages/Join.html","/Market":"pages/Market.html","/Mentor":"pages/Mentor.html","/Login":"pages/Login.html","/Mypage":"pages/Mypage.html","/My":"pages/My.html","/Password":"pages/Password.html","/SearchMentor":"pages/SearchMentor.html","/UDMentor":"pages/UDMentor.html","/Temp":"pages/Temp.html","/UDVolun":"pages/UDVolun.html","/":"pages/index.html","/Chat":"pages/Chat.html","/Search":"pages/Search.html","/register":"pages/register.html","/shrimp":"pages/shrimp.html","/Calendar":"pages/Calendar.html","/_document":"pages/_document.js","/404":"pages/404.html"}