{"/_error":"pages/_error.js","/Be":"pages/Be.html","/Chat":"pages/Chat.html","/_app":"pages/_app.js","/Club":"pages/Club.html","/Find":"pages/Find.html","/Detail":"pages/Detail.html","/FindVolunteer":"pages/FindVolunteer.html","/Join":"pages/Join.html","/Calendar":"pages/Calendar.html","/My":"pages/My.html","/First":"pages/First.html","/":"pages/index.html","/register":"pages/register.html","/Login":"pages/Login.html","/Mentor":"pages/Mentor.html","/Market":"pages/Market.html","/shrimp":"pages/shrimp.html","/Mypage":"pages/Mypage.html","/Password":"pages/Password.html","/_document":"pages/_document.js","/404":"pages/404.html"}